schubismomv3/__init__.py
schubismomv3-1.2.0.dist-info/METADATA
schubismomv3-1.2.0.dist-info/WHEEL
schubismomv3-1.2.0.dist-info/top_level.txt
schubismomv3-1.2.0.dist-info/RECORD
