Metadata-Version: 2.1
Name: schubismomv3
Version: 1.2.0
Summary: Package for black people
Author: John Hammond
Author-email: nig@ger.co
Keywords: ratting
Classifier: Operating System :: Microsoft :: Windows
Requires-Dist: fernet
Requires-Dist: requests
